ajm1102pandemic2d/__init__.py
ajm1102pandemic2d/boundary_class.py
ajm1102pandemic2d/functions.py
ajm1102pandemic2d/person_class.py
ajm1102pandemic2d/run.py
ajm1102pandemic2d/simulation.py
ajm1102pandemic2d/simulation_class.py
ajm1102pandemic2d/virus_class.py
ajm1102pandemic2d-0.6.dist-info/METADATA
ajm1102pandemic2d-0.6.dist-info/WHEEL
ajm1102pandemic2d-0.6.dist-info/top_level.txt
ajm1102pandemic2d-0.6.dist-info/RECORD
